funda_scraper/VERSION
funda_scraper/__init__.py
funda_scraper/preprocess.py
funda_scraper/scrape.py
funda_scraper/utils.py
funda_scraper/config/__init__.py
funda_scraper/config/config.yaml
funda_scraper/config/core.py
funda_scraper-1.2.1.dist-info/LICENSE
funda_scraper-1.2.1.dist-info/METADATA
funda_scraper-1.2.1.dist-info/WHEEL
funda_scraper-1.2.1.dist-info/top_level.txt
funda_scraper-1.2.1.dist-info/RECORD
