Metadata-Version: 2.1
Name: funda-scraper
Version: 1.2.1
Summary: FundaScaper provides you the easiest way to perform web scraping from Funda, the Dutch housing website.
Home-page: https://github.com/whchien/funda-scraper
Author: Will Chien
Author-email: locriginal@gmail.com
License: gpl-3.0
Classifier: License :: OSI Approved :: GNU General Public License v3 (GPLv3)
Classifier: Programming Language :: Python
Classifier: Programming Language :: Python :: 3
Classifier: Programming Language :: Python :: 3.7
Classifier: Programming Language :: Python :: 3.8
Classifier: Programming Language :: Python :: 3.9
Classifier: Programming Language :: Python :: Implementation :: CPython
Classifier: Programming Language :: Python :: Implementation :: PyPy
Requires-Python: >=3.7.0
License-File: LICENSE
Requires-Dist: beautifulsoup4 >=4.8
Requires-Dist: requests >=2
Requires-Dist: diot >=0.1.5
Requires-Dist: PyYAML >=5.0
Requires-Dist: tqdm >=4.42.0
Requires-Dist: pandas >=1.2
Requires-Dist: lxml >=4
Requires-Dist: urllib3 ==1.26
